unrpa/__init__.py
unrpa/__main__.py
unrpa/errors.py
unrpa/meta.py
unrpa/view.py
unrpa/versions/__init__.py
unrpa/versions/alt.py
unrpa/versions/errors.py
unrpa/versions/official_rpa.py
unrpa/versions/unofficial_rpa.py
unrpa/versions/version.py
unrpa/versions/zix.py
unrpa-2.3.0.dist-info/COPYING
unrpa-2.3.0.dist-info/METADATA
unrpa-2.3.0.dist-info/WHEEL
unrpa-2.3.0.dist-info/entry_points.txt
unrpa-2.3.0.dist-info/top_level.txt
unrpa-2.3.0.dist-info/RECORD
