Metadata-Version: 2.1
Name: unrpa
Version: 2.3.0
Summary: Extract files from the RPA archive format (from the Ren'Py Visual Novel Engine).
Home-page: https://github.com/Lattyware/unrpa
Author: Gareth Latty
Author-email: gareth@lattyware.co.uk
License: UNKNOWN
Keywords: renpy rpa archive extract
Platform: UNKNOWN
Classifier: Topic :: System :: Archiving
Classifier: Programming Language :: Python :: 3.7
Classifier: License :: OSI Approved :: GNU General Public License v3 or later (GPLv3+)
Classifier: Operating System :: OS Independent
Classifier: Environment :: Console
Requires-Python: >=3.7
Provides-Extra: ZiX
